{"bodyData": {"bodyContainerBackgroundImage": "url(https://cdn.discordapp.com/attachments/993060883670511646/993061202496344074/20210603_211322.jpg)", "headerImgSrc": "https://cdn.discordapp.com/attachments/993060883670511646/996336833644470333/lxRbckl.png", "menuRowChildren": {"aboutMe": "https://cdn.discordapp.com/attachments/993060883670511646/993061232103927868/aboutMe.png", "myProject": "https://cdn.discordapp.com/attachments/993060883670511646/993061215347671142/myProject.png", "myServer": "https://cdn.discordapp.com/attachments/993060883670511646/993061261313048706/myServer.png"}, "footerRowChildren": {"https://discordapp.com/users/589900887212949522": "https://cdn.discordapp.com/attachments/993060883670511646/997333801405526016/discord.png", "https://github.com/lxRbckl": "https://cdn.discordapp.com/attachments/993060883670511646/997333782673752146/github.png", "mailto:lxrbckl@protonmail.com": "https://cdn.discordapp.com/attachments/993060883670511646/997333749513605120/protonmail.png", "https://github.com/ala2q6": "https://cdn.discordapp.com/attachments/993060883670511646/997333782673752146/github.png", "https://open.spotify.com/user/bop1bgw7rlj4m9sacbnmonjnl?si=d788fefe3e4f4b16": "https://cdn.discordapp.com/attachments/993060883670511646/997333765854609469/spotify.png", "https://www.linkedin.com/in/alexander-arbuckle-857146243/": "https://cdn.discordapp.com/attachments/993060883670511646/997333735655612446/linkedin.png"}}, "bodyStyle": {"bodyContainerStyle": {"top": 0, "left": 0, "margin": 0, "padding": 0, "width": "100%", "height": "100%", "position": "fixed", "overflow-y": "auto", "overflow-x": "hidden", "backgroundSize": "cover", "backgroundAttachment": "fixed"}, "headerRowStyle": {"margin": "1%", "paddingTop": 2}, "headerImgStyle": {"width": 650}, "menuRowStyle": {"margin": "1%", "paddingTop": 12}, "menuImgStyle": {"height": 60}, "bodyRowStyle": {"padding": "1%", "marginLeft": "1%", "marginRight": "1%"}, "footerRowStyle": {"margin": "1%", "paddingTop": 19, "paddingBottom": 15}, "footerImgStyle": {"height": 40}}, "aboutMeData": {"user": ["lxRbckl", "ala2q6"]}, "myServerData": {}, "myProjectData": {}, "templateStyle": {"gBorderRadius": 10, "gBackdropFilter": "blur(10px)", "gColorSolidBlack": "rgba(17, 17, 17, 1)", "gBorderBlack": "2px solid rgb(17, 17, 17)", "gColorSolidWhite": "rgba(248, 240, 227, 1)", "gBorderWhite": "2px solid rgb(248, 240, 227)", "gColorTransparentBlack": "rgba(17, 17, 17, 0.5)", "gColorTransparentWhite": "rgba(248, 240, 227, 0.5)"}, "lxRbckl/lxRbckl": {"topic": ["config", "github-config", "pypl"], "language": {"Python": 2303}, "link": "https://github.com/lxRbckl/lxRbckl", "update": "July 15 2022", "about": {"display": False}}, "lxRbckl/Project-Acta-Mea-1": {"topic": ["discord-py"], "language": {"Python": 2741}, "link": "https://github.com/lxRbckl/Project-Acta-Mea-1", "update": "April 24 2022", "about": None}, "lxRbckl/Project-Acta-Mea-2": {"topic": ["discord-py", "pygithub"], "language": {"Python": 3542}, "link": "https://github.com/lxRbckl/Project-Acta-Mea-2", "update": "May 21 2022", "about": None}, "lxRbckl/Project-Acta-Mea-3": {"topic": ["discord-py", "pygithub"], "language": {"Python": 4144}, "link": "https://github.com/lxRbckl/Project-Acta-Mea-3", "update": "June 09 2022", "about": None}, "lxRbckl/Project-Borg": {"topic": ["xlrd", "xlwt", "matplotlib", "glob"], "language": {"Python": 11479}, "link": "https://github.com/lxRbckl/Project-Borg", "update": "April 24 2022", "about": None}, "lxRbckl/Project-Comperio": {"topic": ["xlrd", "xlwt", "xlutils", "discord-py", "selenium-python", "webdriver-manager"], "language": {"Python": 4353}, "link": "https://github.com/lxRbckl/Project-Comperio", "update": "April 24 2022", "about": None}, "lxRbckl/Project-Domum": {"topic": ["raspberry-pi", "discord-py", "suntime", "rpi-gpio", "asyncio"], "language": {"Python": 8612}, "link": "https://github.com/lxRbckl/Project-Domum", "update": "April 24 2022", "about": None}, "lxRbckl/Project-Fenaverat-1": {"topic": ["dash-python", "selenium-python", "webdriver-manager", "gunicorn", "plotly-python"], "language": {"Python": 26992, "Procfile": 43}, "link": "https://github.com/lxRbckl/Project-Fenaverat-1", "update": "June 04 2022", "about": None}, "lxRbckl/Project-Fenaverat-2": {"topic": [], "language": {"Python": 7980}, "link": "https://github.com/lxRbckl/Project-Fenaverat-2", "update": "July 15 2022", "about": None}, "lxRbckl/Project-Jordyn": {"topic": ["discord-py"], "language": {"Python": 8916}, "link": "https://github.com/lxRbckl/Project-Jordyn", "update": "May 20 2022", "about": None}, "lxRbckl/Project-Maximus": {"topic": ["raspberry-pi", "rpi-gpio", "wmctrl", "guvcview", "plotly-python", "dash-python", "ubuntu", "pytime"], "language": {"Python": 3465, "Shell": 333}, "link": "https://github.com/lxRbckl/Project-Maximus", "update": "April 24 2022", "about": None}, "lxRbckl/Project-Panavia": {"topic": ["plotly-python", "dash-python", "ipinfodb"], "language": {"Python": 14233}, "link": "https://github.com/lxRbckl/Project-Panavia", "update": "April 24 2022", "about": None}, "lxRbckl/Project-PasCam-1": {"topic": ["glob"], "language": {"Python": 17887}, "link": "https://github.com/lxRbckl/Project-PasCam-1", "update": "April 24 2022", "about": None}, "lxRbckl/Project-PasCam-2": {"topic": ["glob"], "language": {"Python": 16205}, "link": "https://github.com/lxRbckl/Project-PasCam-2", "update": "April 24 2022", "about": None}, "lxRbckl/Project-PasCam-3": {"topic": ["glob", "pyperclip"], "language": {"Python": 12146}, "link": "https://github.com/lxRbckl/Project-PasCam-3", "update": "April 24 2022", "about": None}, "lxRbckl/Project-PasCam-4": {"topic": ["discord-py"], "language": {"Python": 3472}, "link": "https://github.com/lxRbckl/Project-PasCam-4", "update": "April 24 2022", "about": None}, "lxRbckl/Project-PasCam-5": {"topic": ["discord-py"], "language": {"Python": 4480}, "link": "https://github.com/lxRbckl/Project-PasCam-5", "update": "April 24 2022", "about": None}, "lxRbckl/Project-PasCam-6": {"topic": ["discord-py"], "language": {"Python": 4966}, "link": "https://github.com/lxRbckl/Project-PasCam-6", "update": "April 24 2022", "about": None}, "lxRbckl/Project-PasCam-7": {"topic": ["discord-py"], "language": {"Python": 9020}, "link": "https://github.com/lxRbckl/Project-PasCam-7", "update": "May 20 2022", "about": None}, "lxRbckl/Project-Serra": {"topic": ["discord-py", "plotly-python", "dash-python"], "language": {"Python": 3899}, "link": "https://github.com/lxRbckl/Project-Serra", "update": "April 24 2022", "about": None}, "lxRbckl/Project-TeneT": {"topic": ["xlwt", "xlrd", "xlutils"], "language": {"Python": 3224}, "link": "https://github.com/lxRbckl/Project-TeneT", "update": "April 24 2022", "about": None}, "lxRbckl/Project-UMKC-1": {"topic": ["asyncio", "discord-py"], "language": {"Python": 3591}, "link": "https://github.com/lxRbckl/Project-UMKC-1", "update": "April 24 2022", "about": None}, "lxRbckl/Project-UMKC-2": {"topic": ["discord-py", "asyncio"], "language": {"Python": 4463}, "link": "https://github.com/lxRbckl/Project-UMKC-2", "update": "April 24 2022", "about": None}, "lxRbckl/Project-WS3K": {"topic": ["discord-py", "webdriver-manager", "selenium-python", "asyncio"], "language": {"Python": 3049}, "link": "https://github.com/lxRbckl/Project-WS3K", "update": "April 24 2022", "about": None}, "ala2q6/ala2q6": {"topic": ["config", "github-config"], "language": {}, "link": "https://github.com/ala2q6/ala2q6", "update": "July 15 2022", "about": None}, "ala2q6/CS201R-P1": {"topic": [], "language": {"C++": 8602}, "link": "https://github.com/ala2q6/CS201R-P1", "update": "May 04 2022", "about": None}, "ala2q6/CS201R-P2": {"topic": [], "language": {"C++": 2531}, "link": "https://github.com/ala2q6/CS201R-P2", "update": "May 04 2022", "about": None}, "ala2q6/CS201R-P3": {"topic": [], "language": {"C++": 7100}, "link": "https://github.com/ala2q6/CS201R-P3", "update": "May 04 2022", "about": None}, "ala2q6/CS201R-P4": {"topic": [], "language": {"C++": 6545}, "link": "https://github.com/ala2q6/CS201R-P4", "update": "May 04 2022", "about": None}, "ala2q6/CS201R-P5": {"topic": [], "language": {"C++": 10150}, "link": "https://github.com/ala2q6/CS201R-P5", "update": "May 04 2022", "about": None}, "ala2q6/CS303-P1": {"topic": [], "language": {"C++": 5434}, "link": "https://github.com/ala2q6/CS303-P1", "update": "May 04 2022", "about": None}, "ala2q6/CS303-P2": {"topic": [], "language": {"C++": 6199}, "link": "https://github.com/ala2q6/CS303-P2", "update": "May 04 2022", "about": None}, "ala2q6/CS441-P2": {"topic": [], "language": {"Clojure": 3950}, "link": "https://github.com/ala2q6/CS441-P2", "update": "May 04 2022", "about": None}, "ala2q6/CS456-P": {"topic": ["dash-python", "gunicorn", "plotly-python"], "language": {"Python": 8710, "Procfile": 25}, "link": "https://github.com/ala2q6/CS456-P", "update": "May 10 2022", "about": None}, "ala2q6/CS461-P1": {"topic": [], "language": {"Python": 1733}, "link": "https://github.com/ala2q6/CS461-P1", "update": "May 04 2022", "about": None}, "ala2q6/CS461-P2": {"topic": [], "language": {"Python": 4620}, "link": "https://github.com/ala2q6/CS461-P2", "update": "May 04 2022", "about": None}, "ala2q6/CS461-P3": {"topic": [], "language": {"Python": 1156}, "link": "https://github.com/ala2q6/CS461-P3", "update": "May 04 2022", "about": None}, "ala2q6/CS490DL-P": {"topic": ["cv2", "dash-python", "keras", "matplotlib", "multiprocessing", "numpy", "pandas", "plotly-python", "sklearn", "tensorflow"], "language": {"Python": 12844}, "link": "https://github.com/ala2q6/CS490DL-P", "update": "May 18 2022", "about": None}, "ala2q6/HARS22": {"topic": ["dash-python", "gunicorn", "plotly-python", "cv2", "keras", "matplotlib", "numpy", "pandas", "sklearn", "tensorflow"], "language": {"Python": 3662, "Procfile": 37}, "link": "https://github.com/ala2q6/HARS22", "update": "May 24 2022", "about": None}}